{
  "dayId": 104,
  "weekId": 10,
  "title": "🪐 Доставка на Марс",
  "estimatedMinutes": 10,
  "tasks": [
    {
      "id": "dream4-t1",
      "type": "calculator",
      "title": "Марсианский revenue",
      "data": {
        "problem": "Сон: вы отправляете трак на Марс! Расстояние: 140,000,000 миль. Rate: $0.001 за милю. Какой total revenue за этот рейс?",
        "context": "140,000,000 миль × $0.001/mile = ?",
        "correctAnswer": 140000,
        "tolerancePercent": 2,
        "unit": "$"
      },
      "hint": "Используйте калькулятор выше — запишите формулу и подставьте числа по шагам."
    },
    {
      "id": "dream4-t2",
      "type": "quiz",
      "title": "Реальный RPM по типам трейлеров",
      "data": {
        "question": "Вернёмся с Марса на Землю. Какой реалистичный target RPM (Revenue Per Mile, всё включено) для reefer в 2024?",
        "options": [
          "Reefer: $1.50/mile, Dry Van: $1.20/mile, Flatbed: $1.80/mile — ниже реального рынка",
          "Reefer: $2.80-$3.50/mile, Dry Van: $2.20-$2.80/mile, Flatbed: $3.00-$4.00/mile — реальные рыночные ставки 2024",
          "Все типы прицепов одинаково по $2.00/mile — без разницы в специализации",
          "Reefer: $5.00+ за милю всегда — только потому что есть холодильное оборудование"
        ],
        "correctIndex": 1,
        "explanation": "RPM зависит от типа оборудования и рынка. Reefer получает premium за температурный контроль ($2.80-$3.50). Dry Van — самый распространённый, больше конкуренции ($2.20-$2.80). Flatbed — specialized + тарпы + load securement ($3.00-$4.00). Это GROSS RPM — до вычета расходов. NET profit обычно 15-30% от gross."
      },
      "hint": "Reefer: $2.80-3.50/mile. Dry Van: $2.20-2.80/mile. Flatbed: $3.00-4.00/mile."
    },
    {
      "id": "dream4-t3",
      "type": "calculator",
      "title": "Стоимость топлива за милю",
      "data": {
        "problem": "Трак расходует 6.2 mpg (miles per gallon). Diesel стоит $4.10/gallon. Сколько стоит топливо НА ОДНУ МИЛЮ?",
        "context": "Cost per mile = цена за галлон ÷ расход (mpg). $4.10 ÷ 6.2 = ?",
        "correctAnswer": 0.66,
        "tolerancePercent": 3,
        "unit": "$/mile"
      },
      "hint": "Используйте калькулятор выше — запишите формулу и подставьте числа по шагам."
    },
    {
      "id": "dream4-t4",
      "type": "calculator",
      "title": "Net profit рейса",
      "data": {
        "problem": "Рейс: gross revenue $4,500 за 1,200 миль. Расходы: fuel (6 mpg, diesel $3.90/gal), dispatch fee 3% от gross, insurance $0.12/mile. Какой NET PROFIT после всех расходов?",
        "context": "Fuel: 1200÷6 = 200 gal × $3.90 = $780. Dispatch: $4,500 × 0.03 = $135. Insurance: 1200 × $0.12 = $144. Net = $4,500 - $780 - $135 - $144 = ?",
        "correctAnswer": 3441,
        "tolerancePercent": 2,
        "unit": "$"
      },
      "hint": "Используйте калькулятор выше — запишите формулу и подставьте числа по шагам."
    },
    {
      "id": "dream4-t5",
      "type": "drag-match",
      "title": "RPM по типам оборудования",
      "data": {
        "pairs": [
          {
            "term": "Dry Van (стандарт)",
            "definition": "$2.20 – $2.80 за милю"
          },
          {
            "term": "Reefer (рефрижератор)",
            "definition": "$2.80 – $3.50 за милю"
          },
          {
            "term": "Flatbed (открытая платформа)",
            "definition": "$3.00 – $4.00 за милю"
          },
          {
            "term": "Step Deck (пониженная платформа)",
            "definition": "$3.20 – $4.20 за милю"
          },
          {
            "term": "Hotshot (pickup + trailer)",
            "definition": "$1.80 – $2.50 за милю"
          }
        ]
      },
      "hint": "Начните с терминов которые знаете точно — остальные встанут на место сами."
    }
  ]
}